merlin_spellbook-0.10.0.dist-info/licenses/LICENSE
spellbook/__init__.py
spellbook/__main__.py
spellbook/log_formatter.py
spellbook/main.py
spellbook/utils.py
spellbook/commands/__init__.py
spellbook/commands/collect.py
spellbook/commands/conduit-collect.py
spellbook/commands/conduit-translate.py
spellbook/commands/learn.py
spellbook/commands/make-barrier-cost.py
spellbook/commands/make-samples.py
spellbook/commands/predict.py
spellbook/commands/serialize.py
spellbook/commands/stack-npz.py
spellbook/commands/translate.py
spellbook/data_formatting/__init__.py
spellbook/data_formatting/collector.py
spellbook/data_formatting/serialize.py
spellbook/data_formatting/stack_npz.py
spellbook/data_formatting/translator.py
spellbook/data_formatting/conduit/__init__.py
spellbook/data_formatting/conduit/python/__init__.py
spellbook/data_formatting/conduit/python/collector.py
spellbook/data_formatting/conduit/python/conduit_bundler.py
spellbook/data_formatting/conduit/python/translator.py
spellbook/ml/__init__.py
spellbook/ml/learn.py
spellbook/ml/learn_alt.py
spellbook/ml/predict.py
spellbook/ml/surrogates.py
spellbook/optimization/__init__.py
spellbook/optimization/qoi.py
spellbook/sampling/__init__.py
spellbook/sampling/make_samples.py
merlin_spellbook-0.10.0.dist-info/METADATA
merlin_spellbook-0.10.0.dist-info/WHEEL
merlin_spellbook-0.10.0.dist-info/entry_points.txt
merlin_spellbook-0.10.0.dist-info/top_level.txt
merlin_spellbook-0.10.0.dist-info/RECORD
