Metadata-Version: 2.4
Name: merlin-spellbook
Version: 0.10.0
Summary: The building blocks of workflows!
Home-page: https://github.com/LLNL/merlin-spellbook
Author: Merlin Dev team
Author-email: merlin@llnl.gov
License: MIT
Keywords: machine learning workflow utilities
Classifier: Programming Language :: Python :: 3.8
Classifier: Programming Language :: Python :: 3.9
Classifier: Programming Language :: Python :: 3.10
Classifier: Programming Language :: Python :: 3.11
Classifier: Programming Language :: Python :: 3.12
Classifier: Programming Language :: Python :: 3.13
License-File: LICENSE
Requires-Dist: importlib_resources; python_version < "3.7"
Requires-Dist: coloredlogs
Requires-Dist: click
Requires-Dist: numpy
Requires-Dist: pyDOE3
Requires-Dist: scipy
Requires-Dist: scikit-learn
Provides-Extra: dev
Requires-Dist: pylint; extra == "dev"
Requires-Dist: black; extra == "dev"
Requires-Dist: dep-license; extra == "dev"
Requires-Dist: flake8; extra == "dev"
Requires-Dist: isort; extra == "dev"
Requires-Dist: pytest; extra == "dev"
Requires-Dist: build; extra == "dev"
Requires-Dist: twine; extra == "dev"
Requires-Dist: sphinx>=2.0.0; extra == "dev"
Requires-Dist: alabaster; extra == "dev"
Dynamic: author
Dynamic: author-email
Dynamic: classifier
Dynamic: description
Dynamic: description-content-type
Dynamic: home-page
Dynamic: keywords
Dynamic: license
Dynamic: license-file
Dynamic: provides-extra
Dynamic: requires-dist
Dynamic: summary
